{"name":"Login","id":"login;login","testSteps":[{"number":1,"description":"1: Login ({email\u003dinggrit@gmail.com, password\u003dPasswordtest321, result\u003dproduct_page})","duration":73261,"startTime":"2022-05-17T16:03:58.337961600+07:00[Asia/Jakarta]","screenshots":[{"screenshot":"5cf5365b44de1eb7e25e8bfd684acd469df441bfc9ffa6df5d63ef113f1f88e8.png","timeStamp":1652778311599}],"result":"SUCCESS","precondition":false,"level":0,"lineNumber":15,"children":[{"number":2,"description":"Given I am on qa.alta.id login page","duration":39361,"startTime":"2022-05-17T16:03:58.571952700+07:00[Asia/Jakarta]","screenshots":[{"screenshot":"6b6563c13227ef0b70a26f8a845b86304c5ded2ac83324d4bda7e0f4416b9ac5.png","timeStamp":1652778277932}],"result":"SUCCESS","precondition":false,"level":1,"children":[{"number":3,"description":"Open url","duration":36477,"startTime":"2022-05-17T16:04:01.424194500+07:00[Asia/Jakarta]","screenshots":[{"screenshot":"6b6563c13227ef0b70a26f8a845b86304c5ded2ac83324d4bda7e0f4416b9ac5.png","timeStamp":1652778277895}],"result":"SUCCESS","precondition":false,"level":2}]},{"number":4,"description":"When I input \"inggrit@gmail.com\"","duration":1707,"startTime":"2022-05-17T16:04:37.949320100+07:00[Asia/Jakarta]","screenshots":[{"screenshot":"6b6563c13227ef0b70a26f8a845b86304c5ded2ac83324d4bda7e0f4416b9ac5.png","timeStamp":1652778278230},{"screenshot":"d96ed1a5ce38d050b6308117c4f9884edc5ba0f17d9aca6abc6a04e7115c9dee.png","timeStamp":1652778279654}],"result":"SUCCESS","precondition":false,"level":1,"children":[{"number":5,"description":"Input email: inggrit@gmail.com","duration":1382,"startTime":"2022-05-17T16:04:38.255464+07:00[Asia/Jakarta]","screenshots":[{"screenshot":"6b6563c13227ef0b70a26f8a845b86304c5ded2ac83324d4bda7e0f4416b9ac5.png","timeStamp":1652778278270},{"screenshot":"d96ed1a5ce38d050b6308117c4f9884edc5ba0f17d9aca6abc6a04e7115c9dee.png","timeStamp":1652778279638}],"result":"SUCCESS","precondition":false,"level":2}]},{"number":6,"description":"And Input \"Passwordtest321\"","duration":1289,"startTime":"2022-05-17T16:04:39.671869100+07:00[Asia/Jakarta]","screenshots":[{"screenshot":"d96ed1a5ce38d050b6308117c4f9884edc5ba0f17d9aca6abc6a04e7115c9dee.png","timeStamp":1652778279679},{"screenshot":"de755253c72014f776d3fd30d779b150e2e5783093fa56073b334693543ebbe4.png","timeStamp":1652778280961}],"result":"SUCCESS","precondition":false,"level":1,"children":[{"number":7,"description":"Input password: Passwordtest321","duration":1231,"startTime":"2022-05-17T16:04:39.712876600+07:00[Asia/Jakarta]","screenshots":[{"screenshot":"c6e2abba5ace299c1b0ea3abc88a2335f8af38d3cd922c31e9fdba84fd386284.png","timeStamp":1652778279989},{"screenshot":"de755253c72014f776d3fd30d779b150e2e5783093fa56073b334693543ebbe4.png","timeStamp":1652778280944}],"result":"SUCCESS","precondition":false,"level":2}]},{"number":8,"description":"And Click login button","duration":29722,"startTime":"2022-05-17T16:04:40.966192100+07:00[Asia/Jakarta]","screenshots":[{"screenshot":"de755253c72014f776d3fd30d779b150e2e5783093fa56073b334693543ebbe4.png","timeStamp":1652778280975},{"screenshot":"5cf5365b44de1eb7e25e8bfd684acd469df441bfc9ffa6df5d63ef113f1f88e8.png","timeStamp":1652778310688}],"result":"SUCCESS","precondition":false,"level":1,"children":[{"number":9,"description":"Click login button","duration":29689,"startTime":"2022-05-17T16:04:40.987197+07:00[Asia/Jakarta]","screenshots":[{"screenshot":"16164a5db08f580fe81b0b2ebf343555696f7ed684d9b5cd5fcc7b7caabf9b39.png","timeStamp":1652778281182},{"screenshot":"5cf5365b44de1eb7e25e8bfd684acd469df441bfc9ffa6df5d63ef113f1f88e8.png","timeStamp":1652778310675}],"result":"SUCCESS","precondition":false,"level":2}]},{"number":10,"description":"Then I get \"product_page\"","duration":887,"startTime":"2022-05-17T16:05:10.693921200+07:00[Asia/Jakarta]","screenshots":[{"screenshot":"5cf5365b44de1eb7e25e8bfd684acd469df441bfc9ffa6df5d63ef113f1f88e8.png","timeStamp":1652778310700},{"screenshot":"5cf5365b44de1eb7e25e8bfd684acd469df441bfc9ffa6df5d63ef113f1f88e8.png","timeStamp":1652778311581}],"result":"SUCCESS","precondition":false,"level":1,"children":[{"number":11,"description":"Product name appears","duration":829,"startTime":"2022-05-17T16:05:10.741933100+07:00[Asia/Jakarta]","screenshots":[{"screenshot":"5cf5365b44de1eb7e25e8bfd684acd469df441bfc9ffa6df5d63ef113f1f88e8.png","timeStamp":1652778311026},{"screenshot":"5cf5365b44de1eb7e25e8bfd684acd469df441bfc9ffa6df5d63ef113f1f88e8.png","timeStamp":1652778311571}],"result":"SUCCESS","precondition":false,"level":2}]}]},{"number":12,"description":"2: Login ({email\u003drosieposieee@wpdork.com, password\u003dPassword123, result\u003dAlert symbol: record not found})","duration":14128,"startTime":"2022-05-17T16:05:13.908428800+07:00[Asia/Jakarta]","screenshots":[{"screenshot":"8033d067d985f387f39dd4c2e14adb451d8ed96b7ce454eaf3434aeb211d1fae.png","timeStamp":1652778328037}],"result":"SUCCESS","precondition":false,"level":0,"lineNumber":16,"children":[{"number":13,"description":"Given I am on qa.alta.id login page","duration":8646,"startTime":"2022-05-17T16:05:13.919435+07:00[Asia/Jakarta]","screenshots":[{"screenshot":"6b6563c13227ef0b70a26f8a845b86304c5ded2ac83324d4bda7e0f4416b9ac5.png","timeStamp":1652778322565}],"result":"SUCCESS","precondition":false,"level":1,"children":[{"number":14,"description":"Open url","duration":8539,"startTime":"2022-05-17T16:05:14.014453200+07:00[Asia/Jakarta]","screenshots":[{"screenshot":"6b6563c13227ef0b70a26f8a845b86304c5ded2ac83324d4bda7e0f4416b9ac5.png","timeStamp":1652778322553}],"result":"SUCCESS","precondition":false,"level":2}]},{"number":15,"description":"When I input \"rosieposieee@wpdork.com\"","duration":1090,"startTime":"2022-05-17T16:05:22.569498400+07:00[Asia/Jakarta]","screenshots":[{"screenshot":"6b6563c13227ef0b70a26f8a845b86304c5ded2ac83324d4bda7e0f4416b9ac5.png","timeStamp":1652778322575},{"screenshot":"c8f59af57475f9135f999eb1dd20949382e2ecaf7384d0f50db291726512da21.png","timeStamp":1652778323660}],"result":"SUCCESS","precondition":false,"level":1,"children":[{"number":16,"description":"Input email: rosieposieee@wpdork.com","duration":1066,"startTime":"2022-05-17T16:05:22.581502800+07:00[Asia/Jakarta]","screenshots":[{"screenshot":"6b6563c13227ef0b70a26f8a845b86304c5ded2ac83324d4bda7e0f4416b9ac5.png","timeStamp":1652778322593},{"screenshot":"c8f59af57475f9135f999eb1dd20949382e2ecaf7384d0f50db291726512da21.png","timeStamp":1652778323648}],"result":"SUCCESS","precondition":false,"level":2}]},{"number":17,"description":"And Input \"Password123\"","duration":1217,"startTime":"2022-05-17T16:05:23.666469400+07:00[Asia/Jakarta]","screenshots":[{"screenshot":"c8f59af57475f9135f999eb1dd20949382e2ecaf7384d0f50db291726512da21.png","timeStamp":1652778323676},{"screenshot":"a8cb2ad1d31594b827f15be817e93854b1c4796ba971fa5730373aabb3cad41b.png","timeStamp":1652778324883}],"result":"SUCCESS","precondition":false,"level":1,"children":[{"number":18,"description":"Input password: Password123","duration":1168,"startTime":"2022-05-17T16:05:23.684473+07:00[Asia/Jakarta]","screenshots":[{"screenshot":"c8f59af57475f9135f999eb1dd20949382e2ecaf7384d0f50db291726512da21.png","timeStamp":1652778323696},{"screenshot":"a8cb2ad1d31594b827f15be817e93854b1c4796ba971fa5730373aabb3cad41b.png","timeStamp":1652778324852}],"result":"SUCCESS","precondition":false,"level":2}]},{"number":19,"description":"And Click login button","duration":2146,"startTime":"2022-05-17T16:05:24.888777200+07:00[Asia/Jakarta]","screenshots":[{"screenshot":"a8cb2ad1d31594b827f15be817e93854b1c4796ba971fa5730373aabb3cad41b.png","timeStamp":1652778324897},{"screenshot":"8033d067d985f387f39dd4c2e14adb451d8ed96b7ce454eaf3434aeb211d1fae.png","timeStamp":1652778327035}],"result":"SUCCESS","precondition":false,"level":1,"children":[{"number":20,"description":"Click login button","duration":1820,"startTime":"2022-05-17T16:05:25.191854300+07:00[Asia/Jakarta]","screenshots":[{"screenshot":"740951115cdcb33e51705c9c04978b9177c969b275052601beecbf93e0a81a43.png","timeStamp":1652778325475},{"screenshot":"8033d067d985f387f39dd4c2e14adb451d8ed96b7ce454eaf3434aeb211d1fae.png","timeStamp":1652778327010}],"result":"SUCCESS","precondition":false,"level":2}]},{"number":21,"description":"Then I get \"Alert symbol: record not found\"","duration":984,"startTime":"2022-05-17T16:05:27.041184+07:00[Asia/Jakarta]","screenshots":[{"screenshot":"8033d067d985f387f39dd4c2e14adb451d8ed96b7ce454eaf3434aeb211d1fae.png","timeStamp":1652778327052},{"screenshot":"8033d067d985f387f39dd4c2e14adb451d8ed96b7ce454eaf3434aeb211d1fae.png","timeStamp":1652778328026}],"result":"SUCCESS","precondition":false,"level":1,"children":[{"number":22,"description":"Error message appears","duration":608,"startTime":"2022-05-17T16:05:27.107198500+07:00[Asia/Jakarta]","screenshots":[{"screenshot":"8033d067d985f387f39dd4c2e14adb451d8ed96b7ce454eaf3434aeb211d1fae.png","timeStamp":1652778327379},{"screenshot":"8033d067d985f387f39dd4c2e14adb451d8ed96b7ce454eaf3434aeb211d1fae.png","timeStamp":1652778327714}],"result":"SUCCESS","precondition":false,"level":2},{"number":23,"description":"Error message equals: Alert symbol: record not found","duration":295,"startTime":"2022-05-17T16:05:27.719417300+07:00[Asia/Jakarta]","screenshots":[{"screenshot":"8033d067d985f387f39dd4c2e14adb451d8ed96b7ce454eaf3434aeb211d1fae.png","timeStamp":1652778327728},{"screenshot":"8033d067d985f387f39dd4c2e14adb451d8ed96b7ce454eaf3434aeb211d1fae.png","timeStamp":1652778328014}],"result":"SUCCESS","precondition":false,"level":2}]}]},{"number":24,"description":"3: Login ({email\u003dpondaaginggrit1@gmail.com, password\u003d, result\u003dAlert message: password is required})","duration":13409,"startTime":"2022-05-17T16:05:29.438823100+07:00[Asia/Jakarta]","screenshots":[{"screenshot":"3374d11e0c9e99c00f32713289db89f281bf4a594eac3e4355b03ac053b29519.png","timeStamp":1652778342847}],"result":"SUCCESS","precondition":false,"level":0,"lineNumber":17,"children":[{"number":25,"description":"Given I am on qa.alta.id login page","duration":8878,"startTime":"2022-05-17T16:05:29.479351600+07:00[Asia/Jakarta]","screenshots":[{"screenshot":"6b6563c13227ef0b70a26f8a845b86304c5ded2ac83324d4bda7e0f4416b9ac5.png","timeStamp":1652778338357}],"result":"SUCCESS","precondition":false,"level":1,"children":[{"number":26,"description":"Open url","duration":8723,"startTime":"2022-05-17T16:05:29.624645400+07:00[Asia/Jakarta]","screenshots":[{"screenshot":"6b6563c13227ef0b70a26f8a845b86304c5ded2ac83324d4bda7e0f4416b9ac5.png","timeStamp":1652778338347}],"result":"SUCCESS","precondition":false,"level":2}]},{"number":27,"description":"When I input \"pondaaginggrit1@gmail.com\"","duration":1220,"startTime":"2022-05-17T16:05:38.362717300+07:00[Asia/Jakarta]","screenshots":[{"screenshot":"6b6563c13227ef0b70a26f8a845b86304c5ded2ac83324d4bda7e0f4416b9ac5.png","timeStamp":1652778338370},{"screenshot":"2478a102e65c3e42ee4c43c69429ef77568cb7d974adb58d2b173175b764f9db.png","timeStamp":1652778339582}],"result":"SUCCESS","precondition":false,"level":1,"children":[{"number":28,"description":"Input email: pondaaginggrit1@gmail.com","duration":1184,"startTime":"2022-05-17T16:05:38.379721400+07:00[Asia/Jakarta]","screenshots":[{"screenshot":"6b6563c13227ef0b70a26f8a845b86304c5ded2ac83324d4bda7e0f4416b9ac5.png","timeStamp":1652778338392},{"screenshot":"2478a102e65c3e42ee4c43c69429ef77568cb7d974adb58d2b173175b764f9db.png","timeStamp":1652778339563}],"result":"SUCCESS","precondition":false,"level":2}]},{"number":29,"description":"And Input \"\"","duration":645,"startTime":"2022-05-17T16:05:39.586205100+07:00[Asia/Jakarta]","screenshots":[{"screenshot":"2478a102e65c3e42ee4c43c69429ef77568cb7d974adb58d2b173175b764f9db.png","timeStamp":1652778339594},{"screenshot":"cdfd8fd7ac9f7ee0ff45fd14e038d5a0797a66e597d4f4e3f5fb9f57399466ea.png","timeStamp":1652778340231}],"result":"SUCCESS","precondition":false,"level":1,"children":[{"number":30,"description":"Input password: ","duration":615,"startTime":"2022-05-17T16:05:39.601210300+07:00[Asia/Jakarta]","screenshots":[{"screenshot":"2478a102e65c3e42ee4c43c69429ef77568cb7d974adb58d2b173175b764f9db.png","timeStamp":1652778339611},{"screenshot":"cdfd8fd7ac9f7ee0ff45fd14e038d5a0797a66e597d4f4e3f5fb9f57399466ea.png","timeStamp":1652778340216}],"result":"SUCCESS","precondition":false,"level":2}]},{"number":31,"description":"And Click login button","duration":1760,"startTime":"2022-05-17T16:05:40.236366400+07:00[Asia/Jakarta]","screenshots":[{"screenshot":"cdfd8fd7ac9f7ee0ff45fd14e038d5a0797a66e597d4f4e3f5fb9f57399466ea.png","timeStamp":1652778340247},{"screenshot":"3374d11e0c9e99c00f32713289db89f281bf4a594eac3e4355b03ac053b29519.png","timeStamp":1652778341997}],"result":"SUCCESS","precondition":false,"level":1,"children":[{"number":32,"description":"Click login button","duration":1730,"startTime":"2022-05-17T16:05:40.254240800+07:00[Asia/Jakarta]","screenshots":[{"screenshot":"351fe16c024178e0193727e0fb9567d76c794afec712570108135b9e6fc5ded6.png","timeStamp":1652778340544},{"screenshot":"3374d11e0c9e99c00f32713289db89f281bf4a594eac3e4355b03ac053b29519.png","timeStamp":1652778341984}],"result":"SUCCESS","precondition":false,"level":2}]},{"number":33,"description":"Then I get \"Alert message: password is required\"","duration":837,"startTime":"2022-05-17T16:05:42.001261900+07:00[Asia/Jakarta]","screenshots":[{"screenshot":"3374d11e0c9e99c00f32713289db89f281bf4a594eac3e4355b03ac053b29519.png","timeStamp":1652778342013},{"screenshot":"3374d11e0c9e99c00f32713289db89f281bf4a594eac3e4355b03ac053b29519.png","timeStamp":1652778342838}],"result":"SUCCESS","precondition":false,"level":1,"children":[{"number":34,"description":"Error message appears","duration":524,"startTime":"2022-05-17T16:05:42.023268400+07:00[Asia/Jakarta]","screenshots":[{"screenshot":"3374d11e0c9e99c00f32713289db89f281bf4a594eac3e4355b03ac053b29519.png","timeStamp":1652778342247},{"screenshot":"3374d11e0c9e99c00f32713289db89f281bf4a594eac3e4355b03ac053b29519.png","timeStamp":1652778342547}],"result":"SUCCESS","precondition":false,"level":2},{"number":35,"description":"Error message equals: Alert message: password is required","duration":273,"startTime":"2022-05-17T16:05:42.555748900+07:00[Asia/Jakarta]","screenshots":[{"screenshot":"3374d11e0c9e99c00f32713289db89f281bf4a594eac3e4355b03ac053b29519.png","timeStamp":1652778342567},{"screenshot":"3374d11e0c9e99c00f32713289db89f281bf4a594eac3e4355b03ac053b29519.png","timeStamp":1652778342828}],"result":"SUCCESS","precondition":false,"level":2}]}]},{"number":36,"description":"4: Login ({email\u003d, password\u003d, result\u003dAlert message: email is required})","duration":14419,"startTime":"2022-05-17T16:05:44.287757600+07:00[Asia/Jakarta]","screenshots":[{"screenshot":"e3f563bdc0aafc81c0b9dccad0a820738abe276d392ea24cf0aa2f5bcc7ad22e.png","timeStamp":1652778358706}],"result":"SUCCESS","precondition":false,"level":0,"lineNumber":18,"children":[{"number":37,"description":"Given I am on qa.alta.id login page","duration":10559,"startTime":"2022-05-17T16:05:44.296757+07:00[Asia/Jakarta]","screenshots":[{"screenshot":"6b6563c13227ef0b70a26f8a845b86304c5ded2ac83324d4bda7e0f4416b9ac5.png","timeStamp":1652778354856}],"result":"SUCCESS","precondition":false,"level":1,"children":[{"number":38,"description":"Open url","duration":10434,"startTime":"2022-05-17T16:05:44.409788900+07:00[Asia/Jakarta]","screenshots":[{"screenshot":"6b6563c13227ef0b70a26f8a845b86304c5ded2ac83324d4bda7e0f4416b9ac5.png","timeStamp":1652778354844}],"result":"SUCCESS","precondition":false,"level":2}]},{"number":39,"description":"When I input \"\"","duration":640,"startTime":"2022-05-17T16:05:54.859529300+07:00[Asia/Jakarta]","screenshots":[{"screenshot":"6b6563c13227ef0b70a26f8a845b86304c5ded2ac83324d4bda7e0f4416b9ac5.png","timeStamp":1652778354866},{"screenshot":"15234c85212788ea1a41af23371cd803d1d3b5936a5eabb1df8fabc6c75e999e.png","timeStamp":1652778355499}],"result":"SUCCESS","precondition":false,"level":1,"children":[{"number":40,"description":"Input email: ","duration":611,"startTime":"2022-05-17T16:05:54.872530+07:00[Asia/Jakarta]","screenshots":[{"screenshot":"6b6563c13227ef0b70a26f8a845b86304c5ded2ac83324d4bda7e0f4416b9ac5.png","timeStamp":1652778354886},{"screenshot":"15234c85212788ea1a41af23371cd803d1d3b5936a5eabb1df8fabc6c75e999e.png","timeStamp":1652778355483}],"result":"SUCCESS","precondition":false,"level":2}]},{"number":41,"description":"And Input \"\"","duration":1132,"startTime":"2022-05-17T16:05:55.504206700+07:00[Asia/Jakarta]","screenshots":[{"screenshot":"15234c85212788ea1a41af23371cd803d1d3b5936a5eabb1df8fabc6c75e999e.png","timeStamp":1652778355514},{"screenshot":"29254aadc0bd3f6be9cc93d35ffa2c9b54f098cb99a37d1492885c7b4a4c0c38.png","timeStamp":1652778356635}],"result":"SUCCESS","precondition":false,"level":1,"children":[{"number":42,"description":"Input password: ","duration":1097,"startTime":"2022-05-17T16:05:55.525212300+07:00[Asia/Jakarta]","screenshots":[{"screenshot":"06fec2ed405d399180305116ee773c892aae00959132fcb037d586085700a23e.png","timeStamp":1652778355800},{"screenshot":"29254aadc0bd3f6be9cc93d35ffa2c9b54f098cb99a37d1492885c7b4a4c0c38.png","timeStamp":1652778356622}],"result":"SUCCESS","precondition":false,"level":2}]},{"number":43,"description":"And Click login button","duration":1421,"startTime":"2022-05-17T16:05:56.640495400+07:00[Asia/Jakarta]","screenshots":[{"screenshot":"29254aadc0bd3f6be9cc93d35ffa2c9b54f098cb99a37d1492885c7b4a4c0c38.png","timeStamp":1652778356650},{"screenshot":"df27b848cd82c3b11a2f6ab9545fb58ff98b931c9af63e572b79798077fc615a.png","timeStamp":1652778358061}],"result":"SUCCESS","precondition":false,"level":1,"children":[{"number":44,"description":"Click login button","duration":1393,"startTime":"2022-05-17T16:05:56.657506200+07:00[Asia/Jakarta]","screenshots":[{"screenshot":"ec437e951d8c9b32aa0e712351711379cf3dbb6652bad28a80ea700a555e5e04.png","timeStamp":1652778356946},{"screenshot":"df27b848cd82c3b11a2f6ab9545fb58ff98b931c9af63e572b79798077fc615a.png","timeStamp":1652778358049}],"result":"SUCCESS","precondition":false,"level":2}]},{"number":45,"description":"Then I get \"Alert message: email is required\"","duration":628,"startTime":"2022-05-17T16:05:58.065862700+07:00[Asia/Jakarta]","screenshots":[{"screenshot":"df27b848cd82c3b11a2f6ab9545fb58ff98b931c9af63e572b79798077fc615a.png","timeStamp":1652778358071},{"screenshot":"e3f563bdc0aafc81c0b9dccad0a820738abe276d392ea24cf0aa2f5bcc7ad22e.png","timeStamp":1652778358694}],"result":"SUCCESS","precondition":false,"level":1,"children":[{"number":46,"description":"Error message appears","duration":318,"startTime":"2022-05-17T16:05:58.077867800+07:00[Asia/Jakarta]","screenshots":[{"screenshot":"df27b848cd82c3b11a2f6ab9545fb58ff98b931c9af63e572b79798077fc615a.png","timeStamp":1652778358086},{"screenshot":"e3f563bdc0aafc81c0b9dccad0a820738abe276d392ea24cf0aa2f5bcc7ad22e.png","timeStamp":1652778358395}],"result":"SUCCESS","precondition":false,"level":2},{"number":47,"description":"Error message equals: Alert message: email is required","duration":285,"startTime":"2022-05-17T16:05:58.398939500+07:00[Asia/Jakarta]","screenshots":[{"screenshot":"e3f563bdc0aafc81c0b9dccad0a820738abe276d392ea24cf0aa2f5bcc7ad22e.png","timeStamp":1652778358408},{"screenshot":"e3f563bdc0aafc81c0b9dccad0a820738abe276d392ea24cf0aa2f5bcc7ad22e.png","timeStamp":1652778358684}],"result":"SUCCESS","precondition":false,"level":2}]}]},{"number":48,"description":"5: Login ({email\u003dpondaaginggrit1@gmail.com, password\u003dPassword4444, result\u003dAlert message: email or password is invalid})","duration":10938,"startTime":"2022-05-17T16:06:00.710924500+07:00[Asia/Jakarta]","screenshots":[{"screenshot":"bb353f1f68cdc1b08daf7d3c8a345b7d44e484bcadf2e0297aae4cc96d629ebe.png","timeStamp":1652778371649}],"result":"SUCCESS","precondition":false,"level":0,"lineNumber":19,"children":[{"number":49,"description":"Given I am on qa.alta.id login page","duration":7295,"startTime":"2022-05-17T16:06:00.716922100+07:00[Asia/Jakarta]","screenshots":[{"screenshot":"6b6563c13227ef0b70a26f8a845b86304c5ded2ac83324d4bda7e0f4416b9ac5.png","timeStamp":1652778368011}],"result":"SUCCESS","precondition":false,"level":1,"children":[{"number":50,"description":"Open url","duration":7230,"startTime":"2022-05-17T16:06:00.774938900+07:00[Asia/Jakarta]","screenshots":[{"screenshot":"6b6563c13227ef0b70a26f8a845b86304c5ded2ac83324d4bda7e0f4416b9ac5.png","timeStamp":1652778368003}],"result":"SUCCESS","precondition":false,"level":2}]},{"number":51,"description":"When I input \"pondaaginggrit1@gmail.com\"","duration":1057,"startTime":"2022-05-17T16:06:08.016975200+07:00[Asia/Jakarta]","screenshots":[{"screenshot":"6b6563c13227ef0b70a26f8a845b86304c5ded2ac83324d4bda7e0f4416b9ac5.png","timeStamp":1652778368022},{"screenshot":"e7c83625db37892194b9249a400869bf2ff1c16372169beecb92dc04d872d4cb.png","timeStamp":1652778369071}],"result":"SUCCESS","precondition":false,"level":1,"children":[{"number":52,"description":"Input email: pondaaginggrit1@gmail.com","duration":1032,"startTime":"2022-05-17T16:06:08.026978700+07:00[Asia/Jakarta]","screenshots":[{"screenshot":"6b6563c13227ef0b70a26f8a845b86304c5ded2ac83324d4bda7e0f4416b9ac5.png","timeStamp":1652778368034},{"screenshot":"e7c83625db37892194b9249a400869bf2ff1c16372169beecb92dc04d872d4cb.png","timeStamp":1652778369059}],"result":"SUCCESS","precondition":false,"level":2}]},{"number":53,"description":"And Input \"Password4444\"","duration":913,"startTime":"2022-05-17T16:06:09.079149200+07:00[Asia/Jakarta]","screenshots":[{"screenshot":"e7c83625db37892194b9249a400869bf2ff1c16372169beecb92dc04d872d4cb.png","timeStamp":1652778369089},{"screenshot":"8939c8d25bcba9b095ffd3717a09eadc1ba3a48181cdbd613adcc6eb5810e41d.png","timeStamp":1652778369992}],"result":"SUCCESS","precondition":false,"level":1,"children":[{"number":54,"description":"Input password: Password4444","duration":883,"startTime":"2022-05-17T16:06:09.095188200+07:00[Asia/Jakarta]","screenshots":[{"screenshot":"e7c83625db37892194b9249a400869bf2ff1c16372169beecb92dc04d872d4cb.png","timeStamp":1652778369103},{"screenshot":"8939c8d25bcba9b095ffd3717a09eadc1ba3a48181cdbd613adcc6eb5810e41d.png","timeStamp":1652778369978}],"result":"SUCCESS","precondition":false,"level":2}]},{"number":55,"description":"And Click login button","duration":1054,"startTime":"2022-05-17T16:06:09.997314500+07:00[Asia/Jakarta]","screenshots":[{"screenshot":"8939c8d25bcba9b095ffd3717a09eadc1ba3a48181cdbd613adcc6eb5810e41d.png","timeStamp":1652778370005},{"screenshot":"1e112cc500ceaebe7606c34d6d9064ef661e4841c977528a3f78abfdf560d515.png","timeStamp":1652778371051}],"result":"SUCCESS","precondition":false,"level":1,"children":[{"number":56,"description":"Click login button","duration":1027,"startTime":"2022-05-17T16:06:10.010319+07:00[Asia/Jakarta]","screenshots":[{"screenshot":"2022b2426a23bc3d5afa9617a33a469c4161baec2f028257df9006087802b34c.png","timeStamp":1652778370251},{"screenshot":"1e112cc500ceaebe7606c34d6d9064ef661e4841c977528a3f78abfdf560d515.png","timeStamp":1652778371037}],"result":"SUCCESS","precondition":false,"level":2}]},{"number":57,"description":"Then I get \"Alert message: email or password is invalid\"","duration":586,"startTime":"2022-05-17T16:06:11.055103+07:00[Asia/Jakarta]","screenshots":[{"screenshot":"1e112cc500ceaebe7606c34d6d9064ef661e4841c977528a3f78abfdf560d515.png","timeStamp":1652778371060},{"screenshot":"bb353f1f68cdc1b08daf7d3c8a345b7d44e484bcadf2e0297aae4cc96d629ebe.png","timeStamp":1652778371641}],"result":"SUCCESS","precondition":false,"level":1,"children":[{"number":58,"description":"Error message appears","duration":268,"startTime":"2022-05-17T16:06:11.067105500+07:00[Asia/Jakarta]","screenshots":[{"screenshot":"1e112cc500ceaebe7606c34d6d9064ef661e4841c977528a3f78abfdf560d515.png","timeStamp":1652778371073},{"screenshot":"bb353f1f68cdc1b08daf7d3c8a345b7d44e484bcadf2e0297aae4cc96d629ebe.png","timeStamp":1652778371334}],"result":"SUCCESS","precondition":false,"level":2},{"number":59,"description":"Error message equals: Alert message: email or password is invalid","duration":296,"startTime":"2022-05-17T16:06:11.337660200+07:00[Asia/Jakarta]","screenshots":[{"screenshot":"bb353f1f68cdc1b08daf7d3c8a345b7d44e484bcadf2e0297aae4cc96d629ebe.png","timeStamp":1652778371355},{"screenshot":"bb353f1f68cdc1b08daf7d3c8a345b7d44e484bcadf2e0297aae4cc96d629ebe.png","timeStamp":1652778371633}],"result":"SUCCESS","precondition":false,"level":2}]}]}],"userStory":{"id":"login","storyName":"Login","displayName":"Login","path":"Login.feature","narrative":"  As a user\n  I have to be able to login\n  So that i can buy products","type":"feature"},"featureTag":{"name":"Login","type":"feature","displayName":"Login"},"title":"Login","description":"","tags":[{"name":"Login","type":"feature","displayName":"Login"}],"startTime":"2022-05-17T16:03:57.706806900+07:00[Asia/Jakarta]","duration":135376,"projectKey":"","driver":"chrome","isManualTestingUpToDate":false,"dataTable":{"headers":["email","password","result"],"rows":[{"values":["inggrit@gmail.com","Passwordtest321","product_page"],"lineNumber":15,"result":"SUCCESS"},{"values":["rosieposieee@wpdork.com","Password123","Alert symbol: record not found"],"lineNumber":16,"result":"SUCCESS"},{"values":["pondaaginggrit1@gmail.com","","Alert message: password is required"],"lineNumber":17,"result":"SUCCESS"},{"values":["","","Alert message: email is required"],"lineNumber":18,"result":"SUCCESS"},{"values":["pondaaginggrit1@gmail.com","Password4444","Alert message: email or password is invalid"],"lineNumber":19,"result":"SUCCESS"}],"predefinedRows":true,"scenarioOutline":"Given I am on qa.alta.id login page\n\rWhen I input \"\u003cemail\u003e\"\n\rAnd Input \"\u003cpassword\u003e\"\n\rAnd Click login button\n\rThen I get \"\u003cresult\u003e\"\n\r","dataSetDescriptors":[{"startRow":0,"rowCount":0,"name":"","description":""}]},"manual":false,"testSource":"Cucumber","result":"SUCCESS","scenarioOutline":"Given I am on qa.alta.id login page\r\nWhen I input \"\u003cemail\u003e\"\r\nAnd Input \"\u003cpassword\u003e\"\r\nAnd Click login button\r\nThen I get \"\u003cresult\u003e\""}